<?xml version="1.0"?>
<ruleset>
	<rule ref="./vendor/mediawiki/mediawiki-codesniffer/MediaWiki">
		<!-- Not applicable -->
		<exclude name="Generic.PHP.NoSilencedErrors.Discouraged" />
		<exclude name="MediaWiki.Commenting.MissingCovers.MissingCovers" />
		<exclude name="MediaWiki.NamingConventions.ValidGlobalName" />
		<exclude name="MediaWiki.Usage.SuperGlobalsUsage.SuperGlobals" />
		<!-- TODO -->
		<exclude name="Generic.Files.LineLength.TooLong" />
		<exclude name="MediaWiki.Commenting.FunctionComment" />
		<exclude name="MediaWiki.Commenting.FunctionComment.MissingReturn" />
		<exclude name="MediaWiki.Commenting.PropertyDocumentation" />
		<exclude name="PSR12.Properties.ConstantVisibility.NotFound" />
	</rule>
	<file>.</file>
	<arg name="encoding" value="UTF-8"/>
	<arg name="extensions" value="php"/>
</ruleset>
